logzero/__init__.py
logzero/colors.py
logzero/jsonlogger.py
logzero-1.6.2.dist-info/LICENSE
logzero-1.6.2.dist-info/METADATA
logzero-1.6.2.dist-info/WHEEL
logzero-1.6.2.dist-info/top_level.txt
logzero-1.6.2.dist-info/RECORD
